nytimes_top_stories-1.0.1.dist-info/DESCRIPTION.rst
nytimes_top_stories-1.0.1.dist-info/METADATA
nytimes_top_stories-1.0.1.dist-info/RECORD
nytimes_top_stories-1.0.1.dist-info/WHEEL
nytimes_top_stories-1.0.1.dist-info/metadata.json
nytimes_top_stories-1.0.1.dist-info/top_level.txt
topstories/__init__.py
topstories/top_stories.py
