Metadata-Version: 2.0
Name: nytimes-top-stories
Version: 1.0.1
Summary: Python wrapper for NYTimes Top Stories API
Home-page: http://github.com/kashiish/nytimes-top-stories
Author: Kashish Arora
Author-email: kashisharora99@gmail.com
License: MIT
Keywords: new york times nytimes top stories api
Platform: UNKNOWN
Classifier: Development Status :: 4 - Beta
Classifier: Intended Audience :: Developers
Classifier: License :: OSI Approved :: MIT License
Classifier: Programming Language :: Python :: 2
Classifier: Programming Language :: Python :: 2.7
Classifier: Programming Language :: Python :: 3
Classifier: Programming Language :: Python :: 3.3
Classifier: Programming Language :: Python :: 3.2
Classifier: Programming Language :: Python :: 3.4
Classifier: Programming Language :: Python :: 3.5
Classifier: Programming Language :: Python :: 3.6
Requires-Dist: requests (>=2.1.0)
